oneat_augmentations/Augmentation2D.py
oneat_augmentations/Augmentation2DC.py
oneat_augmentations/Augmentation3D.py
oneat_augmentations/TemporalAug.py
oneat_augmentations/TemporalZAug.py
oneat_augmentations/__init__.py
oneat_augmentations/_version.py
oneat_augmentations/utils.py
oneat_augmentations-1.0.1.dist-info/LICENSE
oneat_augmentations-1.0.1.dist-info/METADATA
oneat_augmentations-1.0.1.dist-info/WHEEL
oneat_augmentations-1.0.1.dist-info/top_level.txt
oneat_augmentations-1.0.1.dist-info/RECORD
